idc_clustering/idc.py
idc_clustering-1.2.0.dist-info/METADATA
idc_clustering-1.2.0.dist-info/WHEEL
idc_clustering-1.2.0.dist-info/top_level.txt
idc_clustering-1.2.0.dist-info/RECORD
